locobuzz_python_configuration/__init__.py
locobuzz_python_configuration/async_helpers.cp311-win_amd64.pyd
locobuzz_python_configuration/async_helpers.py
locobuzz_python_configuration/aws_config_builder.cp311-win_amd64.pyd
locobuzz_python_configuration/aws_config_builder.py
locobuzz_python_configuration/clickhouse_config_builder.cp311-win_amd64.pyd
locobuzz_python_configuration/clickhouse_config_builder.py
locobuzz_python_configuration/config_builder.cp311-win_amd64.pyd
locobuzz_python_configuration/config_builder.py
locobuzz_python_configuration/elastic_config_builder.cp311-win_amd64.pyd
locobuzz_python_configuration/elastic_config_builder.py
locobuzz_python_configuration/enums_loco.cp311-win_amd64.pyd
locobuzz_python_configuration/enums_loco.py
locobuzz_python_configuration/kafka_config_builder.cp311-win_amd64.pyd
locobuzz_python_configuration/kafka_config_builder.py
locobuzz_python_configuration/logger_config.cp311-win_amd64.pyd
locobuzz_python_configuration/logger_config.py
locobuzz_python_configuration/redis_client.cp311-win_amd64.pyd
locobuzz_python_configuration/redis_client.py
locobuzz_python_configuration/redis_config_builder.cp311-win_amd64.pyd
locobuzz_python_configuration/redis_config_builder.py
locobuzz_python_configuration/sql_config_builder.cp311-win_amd64.pyd
locobuzz_python_configuration/sql_config_builder.py
locobuzz_python_configuration/utils_functions.cp311-win_amd64.pyd
locobuzz_python_configuration/utils_functions.py
locobuzz_python_configuration-0.1.15.dist-info/METADATA
locobuzz_python_configuration-0.1.15.dist-info/WHEEL
locobuzz_python_configuration-0.1.15.dist-info/top_level.txt
locobuzz_python_configuration-0.1.15.dist-info/RECORD
