Metadata-Version: 2.1
Name: locobuzz_python_configuration
Version: 0.1.15
Summary: A configuration builder package
Home-page: https://github.com/LocoBuzz-Solutions-Pvt-Ltd/locobuzz_python_configuration
Author: Sheikh Muhammed Shoaib
Author-email: shoaib.sheikh@locobuzz.com
Classifier: Programming Language :: Python :: 3
Classifier: License :: OSI Approved :: MIT License
Classifier: Operating System :: OS Independent
Requires-Python: >=3.9
Requires-Dist: Cython
Requires-Dist: jsonschema
Requires-Dist: pytz
Requires-Dist: requests
Requires-Dist: aiohttp
